newcustom/__init__.py
newcustom/functions.py
newcustom-0.0.1.dist-info/METADATA
newcustom-0.0.1.dist-info/WHEEL
newcustom-0.0.1.dist-info/top_level.txt
newcustom-0.0.1.dist-info/RECORD
