Metadata-Version: 2.1
Name: newcustom
Version: 0.0.1
Summary: A Python package for NLP tasks and utilities
Home-page: https://github.com/KavyaGJS/nlppack
Author: KavyaGJS
Author-email: kavyamujk@gmail.com
Requires-Dist: click
Requires-Dist: pytz
